BiT
Biodiversity
Channel_Split
ClassBit
Taxonomic
