Metadata-Version: 2.1
Name: Bitdesc
Version: 0.0.2
Summary: Bio-Inspired Texture Descriptor
Home-page: https://github.com/stevetmat/BioInspiredFDesc
Author: Steve Ataky & Alessandro Lameiras
Author-email: steve.ataky@nca.ufma.br
License: MIT
Keywords: texture descriptor invariant bio-inspired
Platform: UNKNOWN
Classifier: Programming Language :: Python :: 3
Classifier: Programming Language :: Python :: 3.6
Classifier: Programming Language :: Python :: 3.7
Classifier: Operating System :: OS Independent
Provides-Extra: dev
